README.md
setup.cfg
setup.py
bin/tims2hdf5.py
timspy/__init__.py
timspy/df.py
timspy/dia.py
timspy/plot.py
timspy/sql.py
timspy/vaex.py
timspy.egg-info/PKG-INFO
timspy.egg-info/SOURCES.txt
timspy.egg-info/dependency_links.txt
timspy.egg-info/requires.txt
timspy.egg-info/top_level.txt