Metadata-Version: 2.1
Name: timspy
Version: 0.9.1
Summary: TimsPy: access for raw timsTOF Pro data for data scientists
Home-page: https://github.com/MatteoLacki/timspy.git
Author: MatteoLacki
Author-email: matteo.lacki@gmail.com
License: UNKNOWN
Keywords: timsTOFpro,numpy,data science,mass spectrometry
Platform: UNKNOWN
Classifier: Development Status :: 1 - Planning
Classifier: License :: OSI Approved :: BSD License
Classifier: Intended Audience :: Science/Research
Classifier: Topic :: Scientific/Engineering :: Chemistry
Classifier: Programming Language :: Python :: 3.6
Classifier: Programming Language :: Python :: 3.7
Classifier: Programming Language :: Python :: 3.8
Provides-Extra: vaex
